{"Jack Harlow": {"name": "Jack Harlow", "songs": [{"title": "Lovin On Me", "author": "Jack Harlow", "rank_curr": 1, "rank_high": 1, "weeks_on_chart": 2, "score": 2.01, "release_date": 2023111000}], "neighbors": {}, "score": null}, "Taylor Swift": {"name": "Taylor Swift", "songs": [{"title": "Cruel Summer", "author": "Taylor Swift", "rank_curr": 2, "rank_high": 1, "weeks_on_chart": 29, "score": 1.8116666666666665, "release_date": 2019082300}, {"title": "Is It Over Now? (Taylor's Version) [From The Vault]", "author": "Taylor Swift", "rank_curr": 9, "rank_high": 1, "weeks_on_chart": 4, "score": 1.22, "release_date": 2023100800}, {"title": "Now That We Don't Talk (Taylor's Version) [From The Vault]", "author": "Taylor Swift", "rank_curr": 56, "rank_high": 2, "weeks_on_chart": 4, "score": 1.0544827586206897, "release_date": 2023100800}, {"title": "Slut! (Taylor's Version) [From The Vault]", "author": "Taylor Swift", "rank_curr": 76, "rank_high": 3, "weeks_on_chart": 4, "score": 1.0453164556962025, "release_date": 2023100800}, {"title": "Say Don't Go (Taylor's Version) [From The Vault]", "author": "Taylor Swift", "rank_curr": 81, "rank_high": 5, "weeks_on_chart": 4, "score": 1.0432558139534884, "release_date": 2020103100}, {"title": "Style (Taylor's Version)", "author": "Taylor Swift", "rank_curr": 91, "rank_high": 9, "weeks_on_chart": 4, "score": 1.04, "release_date": 2023102700}], "neighbors": {}, "score": null}, "Doja Cat": {"name": "Doja Cat", "songs": [{"title": "Paint The Town Red", "author": "Doja Cat", "rank_curr": 3, "rank_high": 1, "weeks_on_chart": 16, "score": 1.58, "release_date": 2023080400}, {"title": "Agora Hills", "author": "Doja Cat", "rank_curr": 19, "rank_high": 14, "weeks_on_chart": 9, "score": 1.1056060606060605, "release_date": 2023092000}], "neighbors": {}, "score": null}, "Mariah Carey": {"name": "Mariah Carey", "songs": [{"title": "All I Want For Christmas Is You", "author": "Mariah Carey", "rank_curr": 4, "rank_high": 1, "weeks_on_chart": 60, "score": 1.7, "release_date": 2019111900}], "neighbors": {}, "score": null}, "SZA": {"name": "SZA", "songs": [{"title": "Snooze", "author": "SZA", "rank_curr": 5, "rank_high": 2, "weeks_on_chart": 50, "score": 1.5357142857142856, "release_date": 2023011800}, {"title": "Rich Baby Daddy", "author": "Drake", "rank_curr": 20, "rank_high": 11, "weeks_on_chart": 7, "score": 1.099516129032258, "release_date": 2023100600}, {"title": "Kill Bill", "author": "SZA", "rank_curr": 49, "rank_high": 1, "weeks_on_chart": 50, "score": 1.29, "release_date": 2023030900}, {"title": "Slime You Out", "author": "Drake", "rank_curr": 74, "rank_high": 1, "weeks_on_chart": 10, "score": 1.0766666666666667, "release_date": 2023091500}], "neighbors": {}, "score": null}, "Zach Bryan": {"name": "Zach Bryan", "songs": [{"title": "I Remember Everything", "author": "Zach Bryan", "rank_curr": 6, "rank_high": 1, "weeks_on_chart": 13, "score": 1.3507142857142855, "release_date": 2023012700}, {"title": "Hey Driver", "author": "Zach Bryan", "rank_curr": 77, "rank_high": 14, "weeks_on_chart": 13, "score": 1.0869780219780218, "release_date": 2023012700}], "neighbors": {}, "score": null}, "Kacey Musgraves": {"name": "Kacey Musgraves", "songs": [{"title": "I Remember Everything", "author": "Zach Bryan", "rank_curr": 6, "rank_high": 1, "weeks_on_chart": 13, "score": 1.3507142857142855, "release_date": 2023012700}], "neighbors": {}, "score": null}, "Tate McRae": {"name": "Tate McRae", "songs": [{"title": "Greedy", "author": "Tate McRae", "rank_curr": 7, "rank_high": 7, "weeks_on_chart": 10, "score": 1.1928571428571428, "release_date": 2023111000}, {"title": "Exes", "author": "Tate McRae", "rank_curr": 34, "rank_high": 34, "weeks_on_chart": 1, "score": 1.0344117647058821, "release_date": 2023111700}], "neighbors": {}, "score": null}, "Brenda Lee": {"name": "Brenda Lee", "songs": [{"title": "Rockin' Around The Christmas Tree", "author": "Brenda Lee", "rank_curr": 8, "rank_high": 2, "weeks_on_chart": 53, "score": 1.4649999999999999, "release_date": 1900010100}], "neighbors": {}, "score": null}, "Tyla": {"name": "Tyla", "songs": [{"title": "Water", "author": "Tyla", "rank_curr": 10, "rank_high": 10, "weeks_on_chart": 8, "score": 1.1400000000000001, "release_date": 2023111700}], "neighbors": {}, "score": null}, "Drake": {"name": "Drake", "songs": [{"title": "You Broke My Heart", "author": "Drake", "rank_curr": 11, "rank_high": 11, "weeks_on_chart": 1, "score": 1.0959090909090907, "release_date": 2023111700}, {"title": "First Person Shooter", "author": "Drake", "rank_curr": 17, "rank_high": 1, "weeks_on_chart": 7, "score": 1.146111111111111, "release_date": 2023100600}, {"title": "Rich Baby Daddy", "author": "Drake", "rank_curr": 20, "rank_high": 11, "weeks_on_chart": 7, "score": 1.099516129032258, "release_date": 2023100600}, {"title": "Evil Ways", "author": "Drake", "rank_curr": 26, "rank_high": 26, "weeks_on_chart": 1, "score": 1.0434615384615384, "release_date": 2023111700}, {"title": "IDGAF", "author": "Drake", "rank_curr": 29, "rank_high": 2, "weeks_on_chart": 7, "score": 1.099516129032258, "release_date": 2023100600}, {"title": "Virginia Beach", "author": "Drake", "rank_curr": 50, "rank_high": 3, "weeks_on_chart": 7, "score": 1.0727358490566037, "release_date": 2023100600}, {"title": "Red Button", "author": "Drake", "rank_curr": 51, "rank_high": 51, "weeks_on_chart": 1, "score": 1.0246078431372547, "release_date": 2023111700}, {"title": "The Shoe Fits", "author": "Drake", "rank_curr": 52, "rank_high": 52, "weeks_on_chart": 1, "score": 1.024230769230769, "release_date": 2023111700}, {"title": "Stories About My Brother", "author": "Drake", "rank_curr": 58, "rank_high": 58, "weeks_on_chart": 1, "score": 1.0222413793103446, "release_date": 2023111700}, {"title": "Wick Man", "author": "Drake", "rank_curr": 71, "rank_high": 71, "weeks_on_chart": 1, "score": 1.0190845070422534, "release_date": 2023111700}, {"title": "Slime You Out", "author": "Drake", "rank_curr": 74, "rank_high": 1, "weeks_on_chart": 10, "score": 1.0766666666666667, "release_date": 2023091500}, {"title": "Meltdown", "author": "Travis Scott", "rank_curr": 94, "rank_high": 3, "weeks_on_chart": 17, "score": 1.1056185567010308, "release_date": 2023072600}, {"title": "Calling For You", "author": "Drake", "rank_curr": 99, "rank_high": 5, "weeks_on_chart": 4, "score": 1.0392307692307692, "release_date": 2023100600}], "neighbors": {}, "score": null}, "Bobby Helms": {"name": "Bobby Helms", "songs": [{"title": "Jingle Bell Rock", "author": "Bobby Helms", "rank_curr": 12, "rank_high": 3, "weeks_on_chart": 51, "score": 1.3883333333333332, "release_date": 2015100100}], "neighbors": {}, "score": null}, "Wham!": {"name": "Wham!", "songs": [{"title": "Last Christmas", "author": "Wham!", "rank_curr": 13, "rank_high": 4, "weeks_on_chart": 33, "score": 1.2826470588235295, "release_date": 1984010100}], "neighbors": {}, "score": null}, "Morgan Wallen": {"name": "Morgan Wallen", "songs": [{"title": "Last Night", "author": "Morgan Wallen", "rank_curr": 14, "rank_high": 1, "weeks_on_chart": 43, "score": 1.3483333333333334, "release_date": 2023053000}, {"title": "Thinkin' Bout Me", "author": "Morgan Wallen", "rank_curr": 15, "rank_high": 7, "weeks_on_chart": 38, "score": 1.2809090909090908, "release_date": 2023030300}, {"title": "Everything I Love", "author": "Morgan Wallen", "rank_curr": 69, "rank_high": 14, "weeks_on_chart": 39, "score": 1.2190963855421688, "release_date": 2023020200}], "neighbors": {}, "score": null}, "Burl Ives": {"name": "Burl Ives", "songs": [{"title": "A Holly Jolly Christmas", "author": "Burl Ives", "rank_curr": 16, "rank_high": 4, "weeks_on_chart": 34, "score": 1.27, "release_date": 1952010100}], "neighbors": {}, "score": null}, "J. Cole": {"name": "J. Cole", "songs": [{"title": "First Person Shooter", "author": "Drake", "rank_curr": 17, "rank_high": 1, "weeks_on_chart": 7, "score": 1.146111111111111, "release_date": 2023100600}, {"title": "Evil Ways", "author": "Drake", "rank_curr": 26, "rank_high": 26, "weeks_on_chart": 1, "score": 1.0434615384615384, "release_date": 2023111700}], "neighbors": {}, "score": null}, "Luke Combs": {"name": "Luke Combs", "songs": [{"title": "Fast Car", "author": "Luke Combs", "rank_curr": 18, "rank_high": 2, "weeks_on_chart": 35, "score": 1.2750000000000001, "release_date": 2023032400}, {"title": "Where The Wild Things Are", "author": "Luke Combs", "rank_curr": 84, "rank_high": 84, "weeks_on_chart": 1, "score": 1.0169047619047618, "release_date": 2023032400}, {"title": "Different 'Round Here", "author": "Riley Green", "rank_curr": 96, "rank_high": 96, "weeks_on_chart": 2, "score": 1.0204166666666667, "release_date": 2019080200}], "neighbors": {}, "score": null}, "Sexyy Red": {"name": "Sexyy Red", "songs": [{"title": "Rich Baby Daddy", "author": "Drake", "rank_curr": 20, "rank_high": 11, "weeks_on_chart": 7, "score": 1.099516129032258, "release_date": 2023100600}, {"title": "SkeeYee", "author": "Sexyy Red", "rank_curr": 88, "rank_high": 62, "weeks_on_chart": 12, "score": 1.0733333333333335, "release_date": 2023101600}], "neighbors": {}, "score": null}, "Jelly Roll": {"name": "Jelly Roll", "songs": [{"title": "Need A Favor", "author": "Jelly Roll", "rank_curr": 21, "rank_high": 13, "weeks_on_chart": 34, "score": 1.2288235294117646, "release_date": 2023083100}, {"title": "Save Me", "author": "Jelly Roll", "rank_curr": 22, "rank_high": 19, "weeks_on_chart": 23, "score": 1.163780487804878, "release_date": 2022010700}, {"title": "Wild Ones", "author": "Jessie Murph", "rank_curr": 60, "rank_high": 42, "weeks_on_chart": 7, "score": 1.0546078431372548, "release_date": 2023102700}], "neighbors": {}, "score": null}, "Lainey Wilson": {"name": "Lainey Wilson", "songs": [{"title": "Save Me", "author": "Jelly Roll", "rank_curr": 22, "rank_high": 19, "weeks_on_chart": 23, "score": 1.163780487804878, "release_date": 2022010700}], "neighbors": {}, "score": null}, "Olivia Rodrigo": {"name": "Olivia Rodrigo", "songs": [{"title": "Vampire", "author": "Olivia Rodrigo", "rank_curr": 23, "rank_high": 1, "weeks_on_chart": 21, "score": 1.1883333333333332, "release_date": 2023063000}, {"title": "Can't Catch Me Now", "author": "Olivia Rodrigo", "rank_curr": 63, "rank_high": 56, "weeks_on_chart": 3, "score": 1.0318067226890755, "release_date": 2023110500}, {"title": "Get Him Back!", "author": "Olivia Rodrigo", "rank_curr": 67, "rank_high": 11, "weeks_on_chart": 11, "score": 1.0806410256410255, "release_date": 2023081800}, {"title": "Bad Idea Right?", "author": "Olivia Rodrigo", "rank_curr": 75, "rank_high": 7, "weeks_on_chart": 15, "score": 1.099390243902439, "release_date": 2023090800}], "neighbors": {}, "score": null}, "Paul Russell": {"name": "Paul Russell", "songs": [{"title": "Lil Boo Thang", "author": "Paul Russell", "rank_curr": 24, "rank_high": 23, "weeks_on_chart": 10, "score": 1.0925531914893618, "release_date": 2023081800}], "neighbors": {}, "score": null}, "Gunna": {"name": "Gunna", "songs": [{"title": "Fukumean", "author": "Gunna", "rank_curr": 25, "rank_high": 4, "weeks_on_chart": 23, "score": 1.1839655172413792, "release_date": 2023051500}], "neighbors": {}, "score": null}, "Chris Stapleton": {"name": "Chris Stapleton", "songs": [{"title": "White Horse", "author": "Chris Stapleton", "rank_curr": 27, "rank_high": 12, "weeks_on_chart": 18, "score": 1.1412820512820514, "release_date": 2023072100}], "neighbors": {}, "score": null}, "Andy Williams": {"name": "Andy Williams", "songs": [{"title": "It's The Most Wonderful Time Of The Year", "author": "Andy Williams", "rank_curr": 28, "rank_high": 5, "weeks_on_chart": 34, "score": 1.2306060606060605, "release_date": 1963101400}], "neighbors": {}, "score": null}, "Yeat": {"name": "Yeat", "songs": [{"title": "IDGAF", "author": "Drake", "rank_curr": 29, "rank_high": 2, "weeks_on_chart": 7, "score": 1.099516129032258, "release_date": 2023100600}], "neighbors": {}, "score": null}, "Miley Cyrus": {"name": "Miley Cyrus", "songs": [{"title": "Used To Be Young", "author": "Miley Cyrus", "rank_curr": 30, "rank_high": 8, "weeks_on_chart": 13, "score": 1.1176315789473683, "release_date": 2023082500}, {"title": "Flowers", "author": "Miley Cyrus", "rank_curr": 47, "rank_high": 1, "weeks_on_chart": 45, "score": 1.2666666666666668, "release_date": 2023011200}], "neighbors": {}, "score": null}, "Dua Lipa": {"name": "Dua Lipa", "songs": [{"title": "Dance The Night", "author": "Dua Lipa", "rank_curr": 31, "rank_high": 6, "weeks_on_chart": 26, "score": 1.1840540540540538, "release_date": 2023063000}, {"title": "Houdini", "author": "Dua Lipa", "rank_curr": 33, "rank_high": 11, "weeks_on_chart": 2, "score": 1.0554545454545454, "release_date": 2023110900}], "neighbors": {}, "score": null}, "Usher": {"name": "Usher", "songs": [{"title": "Good Good", "author": "Usher", "rank_curr": 32, "rank_high": 25, "weeks_on_chart": 15, "score": 1.1100877192982457, "release_date": 2014050500}], "neighbors": {}, "score": null}, "Summer Walker": {"name": "Summer Walker", "songs": [{"title": "Good Good", "author": "Usher", "rank_curr": 32, "rank_high": 25, "weeks_on_chart": 15, "score": 1.1100877192982457, "release_date": 2014050500}], "neighbors": {}, "score": null}, "21 Savage": {"name": "21 Savage", "songs": [{"title": "Good Good", "author": "Usher", "rank_curr": 32, "rank_high": 25, "weeks_on_chart": 15, "score": 1.1100877192982457, "release_date": 2014050500}, {"title": "Turks & Caicos", "author": "Rod Wave", "rank_curr": 86, "rank_high": 24, "weeks_on_chart": 10, "score": 1.0681818181818181, "release_date": 2023091500}, {"title": "Surround Sound", "author": "JID", "rank_curr": 95, "rank_high": 90, "weeks_on_chart": 2, "score": 1.0208108108108107, "release_date": 2022011400}, {"title": "Calling For You", "author": "Drake", "rank_curr": 99, "rank_high": 5, "weeks_on_chart": 4, "score": 1.0392307692307692, "release_date": 2023100600}], "neighbors": {}, "score": null}, "Dean Martin": {"name": "Dean Martin", "songs": [{"title": "Let It Snow, Let It Snow, Let It Snow!", "author": "Dean Martin", "rank_curr": 35, "rank_high": 8, "weeks_on_chart": 26, "score": 1.1765116279069767, "release_date": 1959111600}], "neighbors": {}, "score": null}, "Billie Eilish": {"name": "Billie Eilish", "songs": [{"title": "What Was I Made For?", "author": "Billie Eilish", "rank_curr": 36, "rank_high": 14, "weeks_on_chart": 19, "score": 1.135, "release_date": 2023071300}], "neighbors": {}, "score": null}, "Noah Kahan": {"name": "Noah Kahan", "songs": [{"title": "Stick Season", "author": "Noah Kahan", "rank_curr": 37, "rank_high": 31, "weeks_on_chart": 8, "score": 1.0694117647058823, "release_date": 2023070700}, {"title": "Dial Drunk", "author": "Noah Kahan", "rank_curr": 41, "rank_high": 25, "weeks_on_chart": 23, "score": 1.1453030303030303, "release_date": 2023071800}, {"title": "Northern Attitude", "author": "Noah Kahan", "rank_curr": 79, "rank_high": 37, "weeks_on_chart": 2, "score": 1.0272413793103448, "release_date": 2022101400}], "neighbors": {}, "score": null}, "Bad Bunny": {"name": "Bad Bunny", "songs": [{"title": "Monaco", "author": "Bad Bunny", "rank_curr": 38, "rank_high": 5, "weeks_on_chart": 6, "score": 1.0765116279069769, "release_date": 2023051200}, {"title": "Perro Negro", "author": "Bad Bunny", "rank_curr": 82, "rank_high": 20, "weeks_on_chart": 6, "score": 1.0496078431372549, "release_date": 2023101300}], "neighbors": {}, "score": null}, "Jose Feliciano": {"name": "Jose Feliciano", "songs": [{"title": "Feliz Navidad", "author": "Jose Feliciano", "rank_curr": 39, "rank_high": 6, "weeks_on_chart": 27, "score": 1.1794444444444445, "release_date": 1900010100}], "neighbors": {}, "score": null}, "Teddy Swims": {"name": "Teddy Swims", "songs": [{"title": "Lose Control", "author": "Teddy Swims", "rank_curr": 40, "rank_high": 39, "weeks_on_chart": 15, "score": 1.1003164556962024, "release_date": 2023062300}], "neighbors": {}, "score": null}, "Post Malone": {"name": "Post Malone", "songs": [{"title": "Dial Drunk", "author": "Noah Kahan", "rank_curr": 41, "rank_high": 25, "weeks_on_chart": 23, "score": 1.1453030303030303, "release_date": 2023071800}], "neighbors": {}, "score": null}, "Kelly Clarkson": {"name": "Kelly Clarkson", "songs": [{"title": "Underneath The Tree", "author": "Kelly Clarkson", "rank_curr": 42, "rank_high": 12, "weeks_on_chart": 22, "score": 1.147037037037037, "release_date": 2013102500}], "neighbors": {}, "score": null}, "Nat King Cole": {"name": "Nat King Cole", "songs": [{"title": "The Christmas Song (Merry Christmas To You)", "author": "Nat King Cole", "rank_curr": 43, "rank_high": 9, "weeks_on_chart": 39, "score": 1.2334615384615386, "release_date": 1960010100}], "neighbors": {}, "score": null}, "Mitski": {"name": "Mitski", "songs": [{"title": "My Love Mine All Mine", "author": "Mitski", "rank_curr": 44, "rank_high": 26, "weeks_on_chart": 9, "score": 1.0735714285714284, "release_date": 2023102100}], "neighbors": {}, "score": null}, "Doechii": {"name": "Doechii", "songs": [{"title": "What It Is (Block Boy)", "author": "Doechii", "rank_curr": 45, "rank_high": 29, "weeks_on_chart": 29, "score": 1.172027027027027, "release_date": 2023031700}], "neighbors": {}, "score": null}, "Kodak Black": {"name": "Kodak Black", "songs": [{"title": "What It Is (Block Boy)", "author": "Doechii", "rank_curr": 45, "rank_high": 29, "weeks_on_chart": 29, "score": 1.172027027027027, "release_date": 2023031700}], "neighbors": {}, "score": null}, "The Ronettes": {"name": "The Ronettes", "songs": [{"title": "Sleigh Ride", "author": "The Ronettes", "rank_curr": 46, "rank_high": 10, "weeks_on_chart": 23, "score": 1.1507142857142858, "release_date": 1963112200}], "neighbors": {}, "score": null}, "Ariana Grande": {"name": "Ariana Grande", "songs": [{"title": "Santa Tell Me", "author": "Ariana Grande", "rank_curr": 48, "rank_high": 12, "weeks_on_chart": 19, "score": 1.1283333333333334, "release_date": 2013121300}], "neighbors": {}, "score": null}, "Warren Zeiders": {"name": "Warren Zeiders", "songs": [{"title": "Pretty Little Poison", "author": "Warren Zeiders", "rank_curr": 53, "rank_high": 46, "weeks_on_chart": 11, "score": 1.07520202020202, "release_date": 2023031700}], "neighbors": {}, "score": null}, "Travis Scott": {"name": "Travis Scott", "songs": [{"title": "I Know ?", "author": "Travis Scott", "rank_curr": 54, "rank_high": 11, "weeks_on_chart": 17, "score": 1.1157692307692306, "release_date": 2023072500}, {"title": "Meltdown", "author": "Travis Scott", "rank_curr": 94, "rank_high": 3, "weeks_on_chart": 17, "score": 1.1056185567010308, "release_date": 2023072600}], "neighbors": {}, "score": null}, "Nate Smith": {"name": "Nate Smith", "songs": [{"title": "World On Fire", "author": "Nate Smith", "rank_curr": 55, "rank_high": 47, "weeks_on_chart": 4, "score": 1.0396078431372549, "release_date": 2023042800}], "neighbors": {}, "score": null}, "Fuerza Regida": {"name": "Fuerza Regida", "songs": [{"title": "Harley Quinn", "author": "Fuerza Regida", "rank_curr": 57, "rank_high": 40, "weeks_on_chart": 3, "score": 1.0356185567010308, "release_date": 2023101800}, {"title": "Que Onda", "author": "Calle 24", "rank_curr": 83, "rank_high": 61, "weeks_on_chart": 8, "score": 1.0538888888888889, "release_date": 2023083000}], "neighbors": {}, "score": null}, "Marshmello": {"name": "Marshmello", "songs": [{"title": "Harley Quinn", "author": "Fuerza Regida", "rank_curr": 57, "rank_high": 40, "weeks_on_chart": 3, "score": 1.0356185567010308, "release_date": 2023101800}], "neighbors": {}, "score": null}, "Victoria Monet": {"name": "Victoria Monet", "songs": [{"title": "On My Mama", "author": "Victoria Monet", "rank_curr": 59, "rank_high": 48, "weeks_on_chart": 10, "score": 1.0686915887850468, "release_date": 2023061600}], "neighbors": {}, "score": null}, "Jessie Murph": {"name": "Jessie Murph", "songs": [{"title": "Wild Ones", "author": "Jessie Murph", "rank_curr": 60, "rank_high": 42, "weeks_on_chart": 7, "score": 1.0546078431372548, "release_date": 2023102700}], "neighbors": {}, "score": null}, "Dylan Scott": {"name": "Dylan Scott", "songs": [{"title": "Can't Have Mine", "author": "Dylan Scott", "rank_curr": 61, "rank_high": 57, "weeks_on_chart": 8, "score": 1.0569491525423729, "release_date": 2022021800}], "neighbors": {}, "score": null}, "Lil Tecca": {"name": "Lil Tecca", "songs": [{"title": "500lbs", "author": "Lil Tecca", "rank_curr": 62, "rank_high": 51, "weeks_on_chart": 9, "score": 1.0626991150442477, "release_date": 2023072100}], "neighbors": {}, "score": null}, "Kenya Grace": {"name": "Kenya Grace", "songs": [{"title": "Strangers", "author": "Kenya Grace", "rank_curr": 64, "rank_high": 52, "weeks_on_chart": 10, "score": 1.0672413793103448, "release_date": 2023090100}], "neighbors": {}, "score": null}, "Rod Wave": {"name": "Rod Wave", "songs": [{"title": "Great Gatsby", "author": "Rod Wave", "rank_curr": 65, "rank_high": 30, "weeks_on_chart": 10, "score": 1.0710526315789475, "release_date": 2023091500}, {"title": "Turks & Caicos", "author": "Rod Wave", "rank_curr": 86, "rank_high": 24, "weeks_on_chart": 10, "score": 1.0681818181818181, "release_date": 2023091500}], "neighbors": {}, "score": null}, "HARDY": {"name": "HARDY", "songs": [{"title": "Truck Bed", "author": "HARDY", "rank_curr": 66, "rank_high": 55, "weeks_on_chart": 23, "score": 1.1315289256198346, "release_date": 2022101000}], "neighbors": {}, "score": null}, "Jason Aldean": {"name": "Jason Aldean", "songs": [{"title": "Try That In A Small Town", "author": "Jason Aldean", "rank_curr": 68, "rank_high": 1, "weeks_on_chart": 19, "score": 1.1239855072463767, "release_date": 2023051900}], "neighbors": {}, "score": null}, "Cody Johnson": {"name": "Cody Johnson", "songs": [{"title": "The Painter", "author": "Cody Johnson", "rank_curr": 70, "rank_high": 55, "weeks_on_chart": 7, "score": 1.051, "release_date": 2023081100}], "neighbors": {}, "score": null}, "Karol G": {"name": "Karol G", "songs": [{"title": "Qlona", "author": "Karol G", "rank_curr": 72, "rank_high": 28, "weeks_on_chart": 15, "score": 1.095, "release_date": 2023081000}, {"title": "Mi Ex Tenia Razon", "author": "Karol G", "rank_curr": 100, "rank_high": 22, "weeks_on_chart": 14, "score": 1.086393442622951, "release_date": 2023070700}], "neighbors": {}, "score": null}, "Peso Pluma": {"name": "Peso Pluma", "songs": [{"title": "Qlona", "author": "Karol G", "rank_curr": 72, "rank_high": 28, "weeks_on_chart": 15, "score": 1.095, "release_date": 2023081000}], "neighbors": {}, "score": null}, "Jung Kook": {"name": "Jung Kook", "songs": [{"title": "Standing Next To You", "author": "Jung Kook", "rank_curr": 73, "rank_high": 5, "weeks_on_chart": 3, "score": 1.0406410256410255, "release_date": 2023120100}, {"title": "Too Much", "author": "The Kid LAROI", "rank_curr": 93, "rank_high": 44, "weeks_on_chart": 5, "score": 1.0395985401459853, "release_date": 2023101900}], "neighbors": {}, "score": null}, "The War And Treaty": {"name": "The War And Treaty", "songs": [{"title": "Hey Driver", "author": "Zach Bryan", "rank_curr": 77, "rank_high": 14, "weeks_on_chart": 13, "score": 1.0869780219780218, "release_date": 2023012700}], "neighbors": {}, "score": null}, "Maluma": {"name": "Maluma", "songs": [{"title": "Segun Quien", "author": "Maluma", "rank_curr": 78, "rank_high": 68, "weeks_on_chart": 8, "score": 1.0536986301369864, "release_date": 2023081700}], "neighbors": {}, "score": null}, "Carin Leon": {"name": "Carin Leon", "songs": [{"title": "Segun Quien", "author": "Maluma", "rank_curr": 78, "rank_high": 68, "weeks_on_chart": 8, "score": 1.0536986301369864, "release_date": 2023081700}], "neighbors": {}, "score": null}, "Hozier": {"name": "Hozier", "songs": [{"title": "Northern Attitude", "author": "Noah Kahan", "rank_curr": 79, "rank_high": 37, "weeks_on_chart": 2, "score": 1.0272413793103448, "release_date": 2022101400}], "neighbors": {}, "score": null}, "Parker McCollum": {"name": "Parker McCollum", "songs": [{"title": "Burn It Down", "author": "Parker McCollum", "rank_curr": 80, "rank_high": 77, "weeks_on_chart": 5, "score": 1.0377388535031846, "release_date": 2023051200}], "neighbors": {}, "score": null}, "Feid": {"name": "Feid", "songs": [{"title": "Perro Negro", "author": "Bad Bunny", "rank_curr": 82, "rank_high": 20, "weeks_on_chart": 6, "score": 1.0496078431372549, "release_date": 2023101300}], "neighbors": {}, "score": null}, "Calle 24": {"name": "Calle 24", "songs": [{"title": "Que Onda", "author": "Calle 24", "rank_curr": 83, "rank_high": 61, "weeks_on_chart": 8, "score": 1.0538888888888889, "release_date": 2023083000}], "neighbors": {}, "score": null}, "Chino Pacas": {"name": "Chino Pacas", "songs": [{"title": "Que Onda", "author": "Calle 24", "rank_curr": 83, "rank_high": 61, "weeks_on_chart": 8, "score": 1.0538888888888889, "release_date": 2023083000}], "neighbors": {}, "score": null}, "Oliver Anthony Music": {"name": "Oliver Anthony Music", "songs": [{"title": "Rich Men North Of Richmond", "author": "Oliver Anthony Music", "rank_curr": 85, "rank_high": 1, "weeks_on_chart": 15, "score": 1.0982558139534884, "release_date": 2023081100}], "neighbors": {}, "score": null}, "Dan": {"name": "Dan", "songs": [{"title": "Save Me The Trouble", "author": "Dan", "rank_curr": 87, "rank_high": 84, "weeks_on_chart": 4, "score": 1.0316959064327484, "release_date": 2023071400}], "neighbors": {}, "score": null}, "Shay": {"name": "Shay", "songs": [{"title": "Save Me The Trouble", "author": "Dan", "rank_curr": 87, "rank_high": 84, "weeks_on_chart": 4, "score": 1.0316959064327484, "release_date": 2023071400}], "neighbors": {}, "score": null}, "Myke Towers": {"name": "Myke Towers", "songs": [{"title": "LaLa", "author": "Myke Towers", "rank_curr": 89, "rank_high": 43, "weeks_on_chart": 20, "score": 1.1151515151515152, "release_date": 2023071800}], "neighbors": {}, "score": null}, "Andre 3000": {"name": "Andre 3000", "songs": [{"title": "I Swear, I Really Wanted To Make A \"Rap\" Album But...", "author": "Andre 3000", "rank_curr": 90, "rank_high": 90, "weeks_on_chart": 1, "score": 1.016111111111111, "release_date": 2023111700}], "neighbors": {}, "score": null}, "Grupo Frontera": {"name": "Grupo Frontera", "songs": [{"title": "El Amor de Su Vida", "author": "Grupo Frontera", "rank_curr": 92, "rank_high": 68, "weeks_on_chart": 13, "score": 1.0775, "release_date": 2023080300}], "neighbors": {}, "score": null}, "Grupo Firme": {"name": "Grupo Firme", "songs": [{"title": "El Amor de Su Vida", "author": "Grupo Frontera", "rank_curr": 92, "rank_high": 68, "weeks_on_chart": 13, "score": 1.0775, "release_date": 2023080300}], "neighbors": {}, "score": null}, "The Kid LAROI": {"name": "The Kid LAROI", "songs": [{"title": "Too Much", "author": "The Kid LAROI", "rank_curr": 93, "rank_high": 44, "weeks_on_chart": 5, "score": 1.0395985401459853, "release_date": 2023101900}], "neighbors": {}, "score": null}, "Central Cee": {"name": "Central Cee", "songs": [{"title": "Too Much", "author": "The Kid LAROI", "rank_curr": 93, "rank_high": 44, "weeks_on_chart": 5, "score": 1.0395985401459853, "release_date": 2023101900}], "neighbors": {}, "score": null}, "JID": {"name": "JID", "songs": [{"title": "Surround Sound", "author": "JID", "rank_curr": 95, "rank_high": 90, "weeks_on_chart": 2, "score": 1.0208108108108107, "release_date": 2022011400}], "neighbors": {}, "score": null}, "Baby Tate": {"name": "Baby Tate", "songs": [{"title": "Surround Sound", "author": "JID", "rank_curr": 95, "rank_high": 90, "weeks_on_chart": 2, "score": 1.0208108108108107, "release_date": 2022011400}], "neighbors": {}, "score": null}, "Riley Green": {"name": "Riley Green", "songs": [{"title": "Different 'Round Here", "author": "Riley Green", "rank_curr": 96, "rank_high": 96, "weeks_on_chart": 2, "score": 1.0204166666666667, "release_date": 2019080200}], "neighbors": {}, "score": null}, "Cardi B": {"name": "Cardi B", "songs": [{"title": "Bongos", "author": "Cardi B", "rank_curr": 97, "rank_high": 14, "weeks_on_chart": 11, "score": 1.073018018018018, "release_date": 2023090600}], "neighbors": {}, "score": null}, "Megan Thee Stallion": {"name": "Megan Thee Stallion", "songs": [{"title": "Bongos", "author": "Cardi B", "rank_curr": 97, "rank_high": 14, "weeks_on_chart": 11, "score": 1.073018018018018, "release_date": 2023090600}], "neighbors": {}, "score": null}, "Luke Bryan": {"name": "Luke Bryan", "songs": [{"title": "But I Got A Beer In My Hand", "author": "Luke Bryan", "rank_curr": 98, "rank_high": 92, "weeks_on_chart": 6, "score": 1.0405263157894737, "release_date": 2023050500}], "neighbors": {}, "score": null}}